[
  { "id": "Vanilla", "name": "Guide", "likedBiome": "Forest", "dislikedBiome": "Ocean" },
  { "id": "Vanilla", "name": "Merchant", "likedBiome": "Forest", "dislikedBiome": "Desert" },
  { "id": "Vanilla", "name": "Nurse", "likedBiome": "Hallow", "dislikedBiome": "Snow" },
  { "id": "Vanilla", "name": "Painter", "likedBiome": "Jungle", "dislikedBiome": "Forest" },
  { "id": "Vanilla", "name": "Dye Trader", "likedBiome": "Desert", "dislikedBiome": "Forest" },
  { "id": "Vanilla", "name": "Zoologist", "likedBiome": "Forest", "dislikedBiome": "Desert" },
  { "id": "Vanilla", "name": "Golfer", "likedBiome": "Forest", "dislikedBiome": "Underground" },
  { "id": "Vanilla", "name": "Party Girl", "likedBiome": "Hallow", "dislikedBiome": "Underground" },
  { "id": "Vanilla", "name": "Angler", "likedBiome": "Ocean", "dislikedBiome": "Desert" },
  { "id": "Vanilla", "name": "Stylist", "likedBiome": "Ocean", "dislikedBiome": "Snow" },
  { "id": "Vanilla", "name": "Demolitionist", "likedBiome": "Underground", "dislikedBiome": "Ocean" },
  { "id": "Vanilla", "name": "Dryad", "likedBiome": "Jungle", "dislikedBiome": "Desert" },
  { "id": "Vanilla", "name": "Tavernkeep", "likedBiome": "Hallow", "dislikedBiome": "Snow" },
  { "id": "Vanilla", "name": "Arms Dealer", "likedBiome": "Desert", "dislikedBiome": "Snow" },
  { "id": "Vanilla", "name": "Goblin Tinkerer", "likedBiome": "Underground", "dislikedBiome": "Jungle" },
  { "id": "Vanilla", "name": "Witch Doctor", "likedBiome": "Jungle", "dislikedBiome": "Hallow" },
  { "id": "Vanilla", "name": "Clothier", "likedBiome": "Underground", "dislikedBiome": "Hallow" },
  { "id": "Vanilla", "name": "Mechanic", "likedBiome": "Snow", "dislikedBiome": "Underground" },
  { "id": "Vanilla", "name": "Tax Collector", "likedBiome": "Snow", "dislikedBiome": "Hallow" },
  { "id": "Vanilla", "name": "Pirate", "likedBiome": "Ocean", "dislikedBiome": "Underground" },
  { "id": "Vanilla", "name": "Truffle", "likedBiome": "Mushroom", "dislikedBiome": "None" },
  { "id": "Vanilla", "name": "Wizard", "likedBiome": "Hallow", "dislikedBiome": "Ocean" },
  { "id": "Vanilla", "name": "Steampunker", "likedBiome": "Desert", "dislikedBiome": "Jungle" },
  { "id": "Vanilla", "name": "Cyborg", "likedBiome": "Snow", "dislikedBiome": "Jungle" },
  { "id": "Vanilla", "name": "Santa Claus", "likedBiome": "Snow", "dislikedBiome": "Desert" },
  { "id": "Vanilla", "name": "Princess", "likedBiome": "Any", "dislikedBiome": "None" },

  { "id": "Calamity", "name": "Sea King", "likedBiome": "Ocean", "dislikedBiome": "Desert" },
  { "id": "Calamity", "name": "Bandit", "likedBiome": "Desert", "dislikedBiome": "Jungle" },
  { "id": "Calamity", "name": "Archmage", "likedBiome": "Snow", "dislikedBiome": "Desert" },
  { "id": "Calamity", "name": "Brimstone Witch", "likedBiome": "Forest", "dislikedBiome": "Brimstone Crag" },
  
  { "id": "Thorium", "name": "Cobbler", "likedBiome": "Forest", "dislikedBiome": "Ocean" },
  { "id": "Thorium", "name": "Desert Acolyte", "likedBiome": "Desert", "dislikedBiome": "Jungle" },
  { "id": "Thorium", "name": "Cook", "likedBiome": "Mushroom", "dislikedBiome": "Underground" },
  { "id": "Thorium", "name": "Confused Zombie", "likedBiome": "Forest", "dislikedBiome": "Snow" },
  { "id": "Thorium", "name": "Blacksmith", "likedBiome": "Underground", "dislikedBiome": "None" },
  { "id": "Thorium", "name": "Tracker", "likedBiome": "Snow", "dislikedBiome": "Forest" },
  { "id": "Thorium", "name": "Diverman", "likedBiome": "Ocean", "dislikedBiome": "Desert" },
  { "id": "Thorium", "name": "Druid", "likedBiome": "Jungle", "dislikedBiome": "Snow" },
  { "id": "Thorium", "name": "Spiritualist", "likedBiome": "Hallow", "dislikedBiome": "Underground" },
  { "id": "Thorium", "name": "Weapon Master", "likedBiome": "Underground", "dislikedBiome": "Hallow" },

  { "id": "Fargo's", "name": "Lumberjack", "likedBiome": "Forest", "dislikedBiome": "None" },
  { "id": "Fargo's", "name": "Deviantt", "likedBiome": "Space", "dislikedBiome": "Desert" },
  { "id": "Fargo's", "name": "Abominationn", "likedBiome": "Space", "dislikedBiome": "Dungeon" },
  { "id": "Fargo's", "name": "Mutant", "likedBiome": "Space", "dislikedBiome": "Hallow" },
  { "id": "Fargo's", "name": "Squirrel", "likedBiome": "Forest", "dislikedBiome": "Underground" },

  { "id": "AlchemistNPC", "name": "Alchemist", "likedBiome": "Underground", "dislikedBiome": "Snow" },
  { "id": "AlchemistNPC", "name": "Brewer", "likedBiome": "Forest", "dislikedBiome": "Snow" },
  { "id": "AlchemistNPC", "name": "Jeweler", "likedBiome": "Forest", "dislikedBiome": "Snow" },
  { "id": "AlchemistNPC", "name": "Architect", "likedBiome": "Jungle", "dislikedBiome": "Snow" },
  { "id": "AlchemistNPC", "name": "Operator", "likedBiome": "Snow", "dislikedBiome": "Underground" },
  { "id": "AlchemistNPC", "name": "Musician", "likedBiome": "Hallow", "dislikedBiome": "Snow" },
  { "id": "AlchemistNPC", "name": "Young Brewer", "likedBiome": "Forest", "dislikedBiome": "Snow" },
  { "id": "AlchemistNPC", "name": "Explorer", "likedBiome": "Any", "dislikedBiome": "None" },
  { "id": "AlchemistNPC", "name": "Tinkerer", "likedBiome": "Snow", "dislikedBiome": "Desert" },
  
  { "id": "Redemption", "name": "Zephos", "likedBiome": "Ocean", "dislikedBiome": "Snow" },
  { "id": "Redemption", "name": "Daerel", "likedBiome": "Forest", "dislikedBiome": "Jungle" },
  { "id": "Redemption", "name": "Fool", "likedBiome": "Underground", "dislikedBiome": "Ocean" },
  { "id": "Redemption", "name": "Fallen", "likedBiome": "Caverns", "dislikedBiome": "Hallow" },
  { "id": "Redemption", "name": "Forest Nymph", "likedBiome": "Any", "dislikedBiome": "None" },
  { "id": "Redemption", "name": "Friendly T-Bot", "likedBiome": "Forest", "dislikedBiome": "Snow" },
  
  { "id": "Bosses As NPCs", "name": "King Slime", "likedBiome": "Forest", "dislikedBiome": "Snow" },
  { "id": "Bosses As NPCs", "name": "Eye of Cthulhu", "likedBiome": "Forest", "dislikedBiome": "None" },
  { "id": "Bosses As NPCs", "name": "Eater of Worlds", "likedBiome": "Graveyard", "dislikedBiome": "Hallow" },
  { "id": "Bosses As NPCs", "name": "Brain of Cthulhu", "likedBiome": "Graveyard", "dislikedBiome": "Hallow" },
  { "id": "Bosses As NPCs", "name": "Queen Bee", "likedBiome": "Jungle", "dislikedBiome": "Snow" },
  { "id": "Bosses As NPCs", "name": "Skeletron", "likedBiome": "Graveyard", "dislikedBiome": "None" },
  { "id": "Bosses As NPCs", "name": "Deerclops", "likedBiome": "Snow", "dislikedBiome": "None" },
  { "id": "Bosses As NPCs", "name": "Wall of Flesh", "likedBiome": "Underground", "dislikedBiome": "Forest" },
  { "id": "Bosses As NPCs", "name": "Queen Slime", "likedBiome": "Hallow", "dislikedBiome": "Snow" },
  { "id": "Bosses As NPCs", "name": "The Destroyer", "likedBiome": "Forest", "dislikedBiome": "None" },
  { "id": "Bosses As NPCs", "name": "Retinazer", "likedBiome": "Forest", "dislikedBiome": "None" },
  { "id": "Bosses As NPCs", "name": "Spazmatism", "likedBiome": "Forest", "dislikedBiome": "None" },
  { "id": "Bosses As NPCs", "name": "Skeletron Prime", "likedBiome": "Forest", "dislikedBiome": "None" },
  { "id": "Bosses As NPCs", "name": "Plantera", "likedBiome": "Jungle", "dislikedBiome": "Snow" },
  { "id": "Bosses As NPCs", "name": "Golem", "likedBiome": "Jungle", "dislikedBiome": "Graveyard" },
  { "id": "Bosses As NPCs", "name": "Empress of Light", "likedBiome": "Hallow", "dislikedBiome": "Graveyard" },
  { "id": "Bosses As NPCs", "name": "Duke Fishron", "likedBiome": "Ocean", "dislikedBiome": "None" },
  { "id": "Bosses As NPCs", "name": "Betsy", "likedBiome": "Forest", "dislikedBiome": "Underground" },
  { "id": "Bosses As NPCs", "name": "Lunatic Cultist", "likedBiome": "Graveyard", "dislikedBiome": "None" },
  { "id": "Bosses As NPCs", "name": "Moon Lord", "likedBiome": "Graveyard", "dislikedBiome": "None" },
  { "id": "Bosses As NPCs", "name": "Dreadnautilus", "likedBiome": "Ocean", "dislikedBiome": "Snow" },
  { "id": "Bosses As NPCs", "name": "Mothron", "likedBiome": "Graveyard", "dislikedBiome": "Underground" },
  { "id": "Bosses As NPCs", "name": "Pumpking", "likedBiome": "Graveyard", "dislikedBiome": "Snow" },
  { "id": "Bosses As NPCs", "name": "Ice Queen", "likedBiome": "Snow", "dislikedBiome": "Graveyard" },
  { "id": "Bosses As NPCs", "name": "Martian Saucer", "likedBiome": "Desert", "dislikedBiome": "None" },
  { "id": "Bosses As NPCs", "name": "Torch God", "likedBiome": "Underground", "dislikedBiome": "None" }
]